.dockerignore
.editorconfig
.gitignore
.mergify.yml
.pre-commit-config.yaml
.readthedocs.yml
LICENSE
MANIFEST.in
README.rst
codecov.yml
dev-requirements.txt
docker-compose.yml
ldap-requirements.txt
mysql-requirements.txt
postgresql-requirements.txt
pylintrc
pyproject.toml
requirements.txt
setup.cfg
setup.py
test-requirements.txt
tests.py
tox.ini
bin/kalabash-admin.py
docker/Dockerfile.dev
docker/Dockerfile.front.dev
docker/doveadm
docker/dovecot_config/auth-custom.conf
docker/dovecot_config/dovecot-oauth2.conf.ext
frontend/.browserslistrc
frontend/.editorconfig
frontend/.eslint.conf.js
frontend/.prettierrc.json
frontend/README.md
frontend/gettext.config.cjs
frontend/index.html
frontend/jsconfig.json
frontend/package.json
frontend/vite.config.js
frontend/yarn.lock
frontend/public/config.json
frontend/public/favicon.ico
frontend/src/App.vue
frontend/src/constants.json
frontend/src/main.js
frontend/src/api/account.js
frontend/src/api/accounts.js
frontend/src/api/admin.js
frontend/src/api/alarms.js
frontend/src/api/aliases.js
frontend/src/api/auth.js
frontend/src/api/domains.js
frontend/src/api/identities.js
frontend/src/api/languages.js
frontend/src/api/logs.js
frontend/src/api/parameters.js
frontend/src/api/repository.js
frontend/src/api/senderAddresses.js
frontend/src/api/statistics.js
frontend/src/api/transports.js
frontend/src/api/imap_migration/migrations.js
frontend/src/api/imap_migration/providers.js
frontend/src/assets/kalabash-logo.svg
frontend/src/assets/kalabash.png
frontend/src/assets/kalabash.svg
frontend/src/assets/kalabash_gold.png
frontend/src/assets/logo.png
frontend/src/assets/logo.svg
frontend/src/components/account/APISetupForm.vue
frontend/src/components/account/AutoReplyForm.vue
frontend/src/components/account/BackupCodeAuthForm.vue
frontend/src/components/account/FidoAuthForm.vue
frontend/src/components/account/FilterForm.vue
frontend/src/components/account/FilterSetForm.vue
frontend/src/components/account/ForwardForm.vue
kalabash.egg-info/PKG-INFO
kalabash.egg-info/SOURCES.txt
kalabash.egg-info/dependency_links.txt
kalabash.egg-info/not-zip-safe
kalabash.egg-info/requires.txt
kalabash.egg-info/top_level.txt
