Metadata-Version: 2.1
Name: kalabash
Version: 2.2.14
Summary: Kalabash
Home-page: https://alphamonak.com/
Author: Alphamonak Solutions
Author-email: amonak@alphamonak.com
License: ISC
Keywords: email
Platform: UNKNOWN
Classifier: Development Status :: 5 - Production/Stable
Classifier: Environment :: Web Environment
Classifier: Framework :: Django :: 2.2
Classifier: Intended Audience :: System Administrators
Classifier: License :: OSI Approved :: ISC License (ISCL)
Classifier: Operating System :: OS Independent
Classifier: Programming Language :: Python :: 3
Classifier: Programming Language :: Python :: 3.7
Classifier: Programming Language :: Python :: 3.8
Classifier: Programming Language :: Python :: 3.9
Classifier: Topic :: Communications :: Email
Classifier: Topic :: Internet :: WWW/HTTP
Requires-Python: >=3.7
Provides-Extra: ldap
Provides-Extra: mysql
Provides-Extra: postgresql
Provides-Extra: argon2
License-File: LICENSE
